torchlibrosa/__init__.py
torchlibrosa/augmentation.py
torchlibrosa/stft.py
torchlibrosa-0.1.0.dist-info/LICENSE.md
torchlibrosa-0.1.0.dist-info/METADATA
torchlibrosa-0.1.0.dist-info/WHEEL
torchlibrosa-0.1.0.dist-info/top_level.txt
torchlibrosa-0.1.0.dist-info/RECORD
