Metadata-Version: 2.1
Name: torchlibrosa
Version: 0.1.0
Summary: PyTorch implemention of part of librosa functions.
Home-page: https://github.com/qiuqiangkong/torchlibrosa
Author: Qiuqiang Kong
Author-email: qiuqiangkong@gmail.com
Classifier: Programming Language :: Python :: 3
Classifier: License :: OSI Approved :: MIT License
Classifier: Operating System :: OS Independent
Requires-Python: >=3.6
License-File: LICENSE.md
